tork/main.py
tork-0.0.1.dist-info/LICENSE
tork-0.0.1.dist-info/METADATA
tork-0.0.1.dist-info/WHEEL
tork-0.0.1.dist-info/RECORD
