Metadata-Version: 2.1
Name: tork
Version: 0.0.1
Summary: Edge framework.
License: MIT
Author: ameen-91
Author-email: mohammedameen9011@gmail.com
Requires-Python: >=3.12,<4.0
Classifier: License :: OSI Approved :: MIT License
Classifier: Programming Language :: Python :: 3
Classifier: Programming Language :: Python :: 3.12
Classifier: Programming Language :: Python :: 3.13
